LICENSE
MANIFEST.in
README.rst
setup.py
quad_form_ratio/__init__.py
quad_form_ratio/quad_form_ratio.py
quad_form_ratio.egg-info/PKG-INFO
quad_form_ratio.egg-info/SOURCES.txt
quad_form_ratio.egg-info/dependency_links.txt
quad_form_ratio.egg-info/not-zip-safe
quad_form_ratio.egg-info/requires.txt
quad_form_ratio.egg-info/top_level.txt