Metadata-Version: 1.2
Name: quad-form-ratio
Version: 0.1.0
Summary: Ratios of Normal Quadratic Forms
Home-page: http://github.com/JonasHarnau/quad_form_ratio
Author: Jonas Harnau
Author-email: j.harnau@outlook.com
License: MIT
Platform: UNKNOWN
Classifier: Development Status :: 3 - Alpha
Requires-Python: >=3.6
